stimpack/__init__.py
stimpack/util.py
stimpack/_assets/icon.png
stimpack/device/__init__.py
stimpack/device/daq.py
stimpack/device/locomotion/__init__.py
stimpack/device/locomotion/keytrac/__init__.py
stimpack/device/locomotion/keytrac/keytrac.py
stimpack/device/locomotion/keytrac/keytrac_map.png
stimpack/device/locomotion/loco_managers/__init__.py
stimpack/device/locomotion/loco_managers/keytrac_managers.py
stimpack/device/locomotion/loco_managers/loco_managers.py
stimpack/experiment/__init__.py
stimpack/experiment/client.py
stimpack/experiment/data.py
stimpack/experiment/gui.py
stimpack/experiment/protocol.py
stimpack/experiment/server.py
stimpack/experiment/util/__init__.py
stimpack/experiment/util/config_tools.py
stimpack/experiment/util/h5io.py
stimpack/rpc/__init__.py
stimpack/rpc/echo_server.py
stimpack/rpc/launch.py
stimpack/rpc/multicall.py
stimpack/rpc/transceiver.py
stimpack/rpc/util.py
stimpack/visual_stim/__init__.py
stimpack/visual_stim/base.py
stimpack/visual_stim/distribution.py
stimpack/visual_stim/draw.py
stimpack/visual_stim/framework.py
stimpack/visual_stim/perspective.py
stimpack/visual_stim/screen.py
stimpack/visual_stim/shapes.py
stimpack/visual_stim/shared_pixmap.py
stimpack/visual_stim/square.py
stimpack/visual_stim/stim_server.py
stimpack/visual_stim/stimuli.py
stimpack/visual_stim/trajectory.py
stimpack/visual_stim/util.py
stimpack-0.1.0.dist-info/LICENSE
stimpack-0.1.0.dist-info/METADATA
stimpack-0.1.0.dist-info/WHEEL
stimpack-0.1.0.dist-info/entry_points.txt
stimpack-0.1.0.dist-info/top_level.txt
stimpack-0.1.0.dist-info/RECORD
